<?xml version="1.0"?>
<Level xmlns:xsi="http://www.w3.org/2001/XMLSchema-instance" xmlns:xsd="http://www.w3.org/2001/XMLSchema" Name="Level_01" Visible="true">
    <Layers>
        <Layer Name="Terrain" Visible="true">
            <Items>
                <Item xsi:type="TextureItem" Name="Copy of Texture_0005" Visible="true">
                    <Position>
                        <X>0</X>
                        <Y>128</Y>
                    </Position>
                    <CustomProperties />
                    <Rotation>0</Rotation>
                    <Scale>
                        <X>9920.353</X>
                        <Y>256</Y>
                    </Scale>
                    <TintColor>
                        <R>255</R>
                        <G>255</G>
                        <B>255</B>
                        <A>255</A>
                        <PackedValue>4294967295</PackedValue>
                    </TintColor>
                    <FlipHorizontally>false</FlipHorizontally>
                    <FlipVertically>false</FlipVertically>
                    <texture_filename>whitedot.png</texture_filename>
                    <asset_name>whitedot</asset_name>
                    <Origin>
                        <X>0.5</X>
                        <Y>0.5</Y>
                    </Origin>
                </Item>
                <Item xsi:type="TextureItem" Name="Texture_1652" Visible="true">
                    <Position>
                        <X>-1245</X>
                        <Y>-785</Y>
                    </Position>
                    <CustomProperties />
                    <Rotation>0</Rotation>
                    <Scale>
                        <X>1000</X>
                        <Y>150</Y>
                    </Scale>
                    <TintColor>
                        <R>255</R>
                        <G>255</G>
                        <B>255</B>
                        <A>255</A>
                        <PackedValue>4294967295</PackedValue>
                    </TintColor>
                    <FlipHorizontally>false</FlipHorizontally>
                    <FlipVertically>false</FlipVertically>
                    <texture_filename>whitedot.png</texture_filename>
                    <asset_name>whitedot</asset_name>
                    <Origin>
                        <X>0.5</X>
                        <Y>0.5</Y>
                    </Origin>
                </Item>
                <Item xsi:type="TextureItem" Name="Texture_2185" Visible="true">
                    <Position>
                        <X>1130</X>
                        <Y>8</Y>
                    </Position>
                    <CustomProperties />
                    <Rotation>0</Rotation>
                    <Scale>
                        <X>1186.7644</X>
                        <Y>326.004456</Y>
                    </Scale>
                    <TintColor>
                        <R>255</R>
                        <G>255</G>
                        <B>255</B>
                        <A>255</A>
                        <PackedValue>4294967295</PackedValue>
                    </TintColor>
                    <FlipHorizontally>false</FlipHorizontally>
                    <FlipVertically>false</FlipVertically>
                    <texture_filename>whitedot.png</texture_filename>
                    <asset_name>whitedot</asset_name>
                    <Origin>
                        <X>0.5</X>
                        <Y>0.5</Y>
                    </Origin>
                </Item>
                <Item xsi:type="TextureItem" Name="Texture_2186" Visible="true">
                    <Position>
                        <X>1095</X>
                        <Y>-294</Y>
                    </Position>
                    <CustomProperties />
                    <Rotation>0</Rotation>
                    <Scale>
                        <X>632.941</X>
                        <Y>326.004456</Y>
                    </Scale>
                    <TintColor>
                        <R>255</R>
                        <G>255</G>
                        <B>255</B>
                        <A>255</A>
                        <PackedValue>4294967295</PackedValue>
                    </TintColor>
                    <FlipHorizontally>false</FlipHorizontally>
                    <FlipVertically>false</FlipVertically>
                    <texture_filename>whitedot.png</texture_filename>
                    <asset_name>whitedot</asset_name>
                    <Origin>
                        <X>0.5</X>
                        <Y>0.5</Y>
                    </Origin>
                </Item>
                <Item xsi:type="TextureItem" Name="Texture_2242" Visible="true">
                    <Position>
                        <X>892</X>
                        <Y>-285</Y>
                    </Position>
                    <CustomProperties />
                    <Rotation>0</Rotation>
                    <Scale>
                        <X>632.941</X>
                        <Y>326.004456</Y>
                    </Scale>
                    <TintColor>
                        <R>255</R>
                        <G>255</G>
                        <B>255</B>
                        <A>255</A>
                        <PackedValue>4294967295</PackedValue>
                    </TintColor>
                    <FlipHorizontally>false</FlipHorizontally>
                    <FlipVertically>false</FlipVertically>
                    <texture_filename>whitedot.png</texture_filename>
                    <asset_name>whitedot</asset_name>
                    <Origin>
                        <X>0.5</X>
                        <Y>0.5</Y>
                    </Origin>
                </Item>
                <Item xsi:type="TextureItem" Name="Texture_2243" Visible="true">
                    <Position>
                        <X>1453</X>
                        <Y>-101</Y>
                    </Position>
                    <CustomProperties />
                    <Rotation>0.9875332</Rotation>
                    <Scale>
                        <X>632.941</X>
                        <Y>326.004456</Y>
                    </Scale>
                    <TintColor>
                        <R>255</R>
                        <G>255</G>
                        <B>255</B>
                        <A>255</A>
                        <PackedValue>4294967295</PackedValue>
                    </TintColor>
                    <FlipHorizontally>false</FlipHorizontally>
                    <FlipVertically>false</FlipVertically>
                    <texture_filename>whitedot.png</texture_filename>
                    <asset_name>whitedot</asset_name>
                    <Origin>
                        <X>0.5</X>
                        <Y>0.5</Y>
                    </Origin>
                </Item>
                <Item xsi:type="TextureItem" Name="Texture_2244" Visible="true">
                    <Position>
                        <X>1069</X>
                        <Y>-489</Y>
                    </Position>
                    <CustomProperties />
                    <Rotation>0.998031</Rotation>
                    <Scale>
                        <X>413.8479</X>
                        <Y>213.15773</Y>
                    </Scale>
                    <TintColor>
                        <R>255</R>
                        <G>255</G>
                        <B>255</B>
                        <A>255</A>
                        <PackedValue>4294967295</PackedValue>
                    </TintColor>
                    <FlipHorizontally>false</FlipHorizontally>
                    <FlipVertically>false</FlipVertically>
                    <texture_filename>whitedot.png</texture_filename>
                    <asset_name>whitedot</asset_name>
                    <Origin>
                        <X>0.5</X>
                        <Y>0.5</Y>
                    </Origin>
                </Item>
                <Item xsi:type="TextureItem" Name="Texture_2245" Visible="true">
                    <Position>
                        <X>892</X>
                        <Y>35</Y>
                    </Position>
                    <CustomProperties />
                    <Rotation>0</Rotation>
                    <Scale>
                        <X>632.941</X>
                        <Y>326.004456</Y>
                    </Scale>
                    <TintColor>
                        <R>255</R>
                        <G>255</G>
                        <B>255</B>
                        <A>255</A>
                        <PackedValue>4294967295</PackedValue>
                    </TintColor>
                    <FlipHorizontally>false</FlipHorizontally>
                    <FlipVertically>false</FlipVertically>
                    <texture_filename>whitedot.png</texture_filename>
                    <asset_name>whitedot</asset_name>
                    <Origin>
                        <X>0.5</X>
                        <Y>0.5</Y>
                    </Origin>
                </Item>
                <Item xsi:type="TextureItem" Name="Texture_2247" Visible="true">
                    <Position>
                        <X>944</X>
                        <Y>-583</Y>
                    </Position>
                    <CustomProperties />
                    <Rotation>0</Rotation>
                    <Scale>
                        <X>200</X>
                        <Y>276.911682</Y>
                    </Scale>
                    <TintColor>
                        <R>255</R>
                        <G>255</G>
                        <B>255</B>
                        <A>255</A>
                        <PackedValue>4294967295</PackedValue>
                    </TintColor>
                    <FlipHorizontally>false</FlipHorizontally>
                    <FlipVertically>false</FlipVertically>
                    <texture_filename>whitedot.png</texture_filename>
                    <asset_name>whitedot</asset_name>
                    <Origin>
                        <X>0.5</X>
                        <Y>0.5</Y>
                    </Origin>
                </Item>
                <Item xsi:type="TextureItem" Name="Texture_2248" Visible="true">
                    <Position>
                        <X>1931</X>
                        <Y>139</Y>
                    </Position>
                    <CustomProperties />
                    <Rotation>0.482463241</Rotation>
                    <Scale>
                        <X>632.941</X>
                        <Y>326.004456</Y>
                    </Scale>
                    <TintColor>
                        <R>255</R>
                        <G>255</G>
                        <B>255</B>
                        <A>255</A>
                        <PackedValue>4294967295</PackedValue>
                    </TintColor>
                    <FlipHorizontally>false</FlipHorizontally>
                    <FlipVertically>false</FlipVertically>
                    <texture_filename>whitedot.png</texture_filename>
                    <asset_name>whitedot</asset_name>
                    <Origin>
                        <X>0.5</X>
                        <Y>0.5</Y>
                    </Origin>
                </Item>
                <Item xsi:type="TextureItem" Name="Texture_2263" Visible="true">
                    <Position>
                        <X>-1429</X>
                        <Y>-515</Y>
                    </Position>
                    <CustomProperties />
                    <Rotation>0</Rotation>
                    <Scale>
                        <X>1000</X>
                        <Y>412.050354</Y>
                    </Scale>
                    <TintColor>
                        <R>255</R>
                        <G>255</G>
                        <B>255</B>
                        <A>255</A>
                        <PackedValue>4294967295</PackedValue>
                    </TintColor>
                    <FlipHorizontally>false</FlipHorizontally>
                    <FlipVertically>false</FlipVertically>
                    <texture_filename>whitedot.png</texture_filename>
                    <asset_name>whitedot</asset_name>
                    <Origin>
                        <X>0.5</X>
                        <Y>0.5</Y>
                    </Origin>
                </Item>
                <Item xsi:type="TextureItem" Name="Texture_2264" Visible="true">
                    <Position>
                        <X>-1443</X>
                        <Y>-116</Y>
                    </Position>
                    <CustomProperties />
                    <Rotation>0</Rotation>
                    <Scale>
                        <X>1000</X>
                        <Y>412.050354</Y>
                    </Scale>
                    <TintColor>
                        <R>255</R>
                        <G>255</G>
                        <B>255</B>
                        <A>255</A>
                        <PackedValue>4294967295</PackedValue>
                    </TintColor>
                    <FlipHorizontally>false</FlipHorizontally>
                    <FlipVertically>false</FlipVertically>
                    <texture_filename>whitedot.png</texture_filename>
                    <asset_name>whitedot</asset_name>
                    <Origin>
                        <X>0.5</X>
                        <Y>0.5</Y>
                    </Origin>
                </Item>
                <Item xsi:type="TextureItem" Name="Texture_2265" Visible="true">
                    <Position>
                        <X>824</X>
                        <Y>-550</Y>
                    </Position>
                    <CustomProperties />
                    <Rotation>-0.514172554</Rotation>
                    <Scale>
                        <X>200</X>
                        <Y>276.911682</Y>
                    </Scale>
                    <TintColor>
                        <R>255</R>
                        <G>255</G>
                        <B>255</B>
                        <A>255</A>
                        <PackedValue>4294967295</PackedValue>
                    </TintColor>
                    <FlipHorizontally>false</FlipHorizontally>
                    <FlipVertically>false</FlipVertically>
                    <texture_filename>whitedot.png</texture_filename>
                    <asset_name>whitedot</asset_name>
                    <Origin>
                        <X>0.5</X>
                        <Y>0.5</Y>
                    </Origin>
                </Item>
                <Item xsi:type="TextureItem" Name="Texture_2266" Visible="true">
                    <Position>
                        <X>689</X>
                        <Y>-451</Y>
                    </Position>
                    <CustomProperties />
                    <Rotation>-0.7377889</Rotation>
                    <Scale>
                        <X>200</X>
                        <Y>276.911682</Y>
                    </Scale>
                    <TintColor>
                        <R>255</R>
                        <G>255</G>
                        <B>255</B>
                        <A>255</A>
                        <PackedValue>4294967295</PackedValue>
                    </TintColor>
                    <FlipHorizontally>false</FlipHorizontally>
                    <FlipVertically>false</FlipVertically>
                    <texture_filename>whitedot.png</texture_filename>
                    <asset_name>whitedot</asset_name>
                    <Origin>
                        <X>0.5</X>
                        <Y>0.5</Y>
                    </Origin>
                </Item>
                <Item xsi:type="TextureItem" Name="Texture_2267" Visible="true">
                    <Position>
                        <X>570</X>
                        <Y>-322</Y>
                    </Position>
                    <CustomProperties />
                    <Rotation>-0.904469967</Rotation>
                    <Scale>
                        <X>200</X>
                        <Y>276.911682</Y>
                    </Scale>
                    <TintColor>
                        <R>255</R>
                        <G>255</G>
                        <B>255</B>
                        <A>255</A>
                        <PackedValue>4294967295</PackedValue>
                    </TintColor>
                    <FlipHorizontally>false</FlipHorizontally>
                    <FlipVertically>false</FlipVertically>
                    <texture_filename>whitedot.png</texture_filename>
                    <asset_name>whitedot</asset_name>
                    <Origin>
                        <X>0.5</X>
                        <Y>0.5</Y>
                    </Origin>
                </Item>
                <Item xsi:type="TextureItem" Name="Texture_2268" Visible="true">
                    <Position>
                        <X>462</X>
                        <Y>-207</Y>
                    </Position>
                    <CustomProperties />
                    <Rotation>-0.6139674</Rotation>
                    <Scale>
                        <X>200</X>
                        <Y>276.911682</Y>
                    </Scale>
                    <TintColor>
                        <R>255</R>
                        <G>255</G>
                        <B>255</B>
                        <A>255</A>
                        <PackedValue>4294967295</PackedValue>
                    </TintColor>
                    <FlipHorizontally>false</FlipHorizontally>
                    <FlipVertically>false</FlipVertically>
                    <texture_filename>whitedot.png</texture_filename>
                    <asset_name>whitedot</asset_name>
                    <Origin>
                        <X>0.5</X>
                        <Y>0.5</Y>
                    </Origin>
                </Item>
                <Item xsi:type="TextureItem" Name="Texture_2269" Visible="true">
                    <Position>
                        <X>315</X>
                        <Y>-126</Y>
                    </Position>
                    <CustomProperties />
                    <Rotation>-0.288853168</Rotation>
                    <Scale>
                        <X>200</X>
                        <Y>276.911682</Y>
                    </Scale>
                    <TintColor>
                        <R>255</R>
                        <G>255</G>
                        <B>255</B>
                        <A>255</A>
                        <PackedValue>4294967295</PackedValue>
                    </TintColor>
                    <FlipHorizontally>false</FlipHorizontally>
                    <FlipVertically>false</FlipVertically>
                    <texture_filename>whitedot.png</texture_filename>
                    <asset_name>whitedot</asset_name>
                    <Origin>
                        <X>0.5</X>
                        <Y>0.5</Y>
                    </Origin>
                </Item>
                <Item xsi:type="TextureItem" Name="Texture_2270" Visible="true">
                    <Position>
                        <X>158</X>
                        <Y>-87</Y>
                    </Position>
                    <CustomProperties />
                    <Rotation>-0.207075715</Rotation>
                    <Scale>
                        <X>200</X>
                        <Y>276.911682</Y>
                    </Scale>
                    <TintColor>
                        <R>255</R>
                        <G>255</G>
                        <B>255</B>
                        <A>255</A>
                        <PackedValue>4294967295</PackedValue>
                    </TintColor>
                    <FlipHorizontally>false</FlipHorizontally>
                    <FlipVertically>false</FlipVertically>
                    <texture_filename>whitedot.png</texture_filename>
                    <asset_name>whitedot</asset_name>
                    <Origin>
                        <X>0.5</X>
                        <Y>0.5</Y>
                    </Origin>
                </Item>
                <Item xsi:type="TextureItem" Name="Texture_2271" Visible="true">
                    <Position>
                        <X>-31</X>
                        <Y>-64</Y>
                    </Position>
                    <CustomProperties />
                    <Rotation>-0.0439282656</Rotation>
                    <Scale>
                        <X>200</X>
                        <Y>276.911682</Y>
                    </Scale>
                    <TintColor>
                        <R>255</R>
                        <G>255</G>
                        <B>255</B>
                        <A>255</A>
                        <PackedValue>4294967295</PackedValue>
                    </TintColor>
                    <FlipHorizontally>false</FlipHorizontally>
                    <FlipVertically>false</FlipVertically>
                    <texture_filename>whitedot.png</texture_filename>
                    <asset_name>whitedot</asset_name>
                    <Origin>
                        <X>0.5</X>
                        <Y>0.5</Y>
                    </Origin>
                </Item>
                <Item xsi:type="TextureItem" Name="Texture_2272" Visible="true">
                    <Position>
                        <X>-203</X>
                        <Y>-40</Y>
                    </Position>
                    <CustomProperties />
                    <Rotation>-0.2290703</Rotation>
                    <Scale>
                        <X>200</X>
                        <Y>276.911682</Y>
                    </Scale>
                    <TintColor>
                        <R>255</R>
                        <G>255</G>
                        <B>255</B>
                        <A>255</A>
                        <PackedValue>4294967295</PackedValue>
                    </TintColor>
                    <FlipHorizontally>false</FlipHorizontally>
                    <FlipVertically>false</FlipVertically>
                    <texture_filename>whitedot.png</texture_filename>
                    <asset_name>whitedot</asset_name>
                    <Origin>
                        <X>0.5</X>
                        <Y>0.5</Y>
                    </Origin>
                </Item>
                <Item xsi:type="TextureItem" Name="Texture_2273" Visible="true">
                    <Position>
                        <X>-345</X>
                        <Y>17</Y>
                    </Position>
                    <CustomProperties />
                    <Rotation>-0.534398556</Rotation>
                    <Scale>
                        <X>200</X>
                        <Y>276.911682</Y>
                    </Scale>
                    <TintColor>
                        <R>255</R>
                        <G>255</G>
                        <B>255</B>
                        <A>255</A>
                        <PackedValue>4294967295</PackedValue>
                    </TintColor>
                    <FlipHorizontally>false</FlipHorizontally>
                    <FlipVertically>false</FlipVertically>
                    <texture_filename>whitedot.png</texture_filename>
                    <asset_name>whitedot</asset_name>
                    <Origin>
                        <X>0.5</X>
                        <Y>0.5</Y>
                    </Origin>
                </Item>
                <Item xsi:type="TextureItem" Name="Texture_2274" Visible="true">
                    <Position>
                        <X>-480</X>
                        <Y>50</Y>
                    </Position>
                    <CustomProperties />
                    <Rotation>-0.8198955</Rotation>
                    <Scale>
                        <X>122.530762</X>
                        <Y>169.650986</Y>
                    </Scale>
                    <TintColor>
                        <R>255</R>
                        <G>255</G>
                        <B>255</B>
                        <A>255</A>
                        <PackedValue>4294967295</PackedValue>
                    </TintColor>
                    <FlipHorizontally>false</FlipHorizontally>
                    <FlipVertically>false</FlipVertically>
                    <texture_filename>whitedot.png</texture_filename>
                    <asset_name>whitedot</asset_name>
                    <Origin>
                        <X>0.5</X>
                        <Y>0.5</Y>
                    </Origin>
                </Item>
                <Item xsi:type="TextureItem" Name="Texture_2275" Visible="true">
                    <Position>
                        <X>596</X>
                        <Y>-13</Y>
                    </Position>
                    <CustomProperties />
                    <Rotation>0</Rotation>
                    <Scale>
                        <X>632.941</X>
                        <Y>326.004456</Y>
                    </Scale>
                    <TintColor>
                        <R>255</R>
                        <G>255</G>
                        <B>255</B>
                        <A>255</A>
                        <PackedValue>4294967295</PackedValue>
                    </TintColor>
                    <FlipHorizontally>false</FlipHorizontally>
                    <FlipVertically>false</FlipVertically>
                    <texture_filename>whitedot.png</texture_filename>
                    <asset_name>whitedot</asset_name>
                    <Origin>
                        <X>0.5</X>
                        <Y>0.5</Y>
                    </Origin>
                </Item>
                <Item xsi:type="TextureItem" Name="Texture_2276" Visible="true">
                    <Position>
                        <X>-854</X>
                        <Y>-736</Y>
                    </Position>
                    <CustomProperties />
                    <Rotation>1.19350207</Rotation>
                    <Scale>
                        <X>127.654816</X>
                        <Y>176.745544</Y>
                    </Scale>
                    <TintColor>
                        <R>255</R>
                        <G>255</G>
                        <B>255</B>
                        <A>255</A>
                        <PackedValue>4294967295</PackedValue>
                    </TintColor>
                    <FlipHorizontally>false</FlipHorizontally>
                    <FlipVertically>false</FlipVertically>
                    <texture_filename>whitedot.png</texture_filename>
                    <asset_name>whitedot</asset_name>
                    <Origin>
                        <X>0.5</X>
                        <Y>0.5</Y>
                    </Origin>
                </Item>
                <Item xsi:type="TextureItem" Name="Texture_2277" Visible="true">
                    <Position>
                        <X>-942</X>
                        <Y>-616</Y>
                    </Position>
                    <CustomProperties />
                    <Rotation>0.245980084</Rotation>
                    <Scale>
                        <X>127.654816</X>
                        <Y>176.745544</Y>
                    </Scale>
                    <TintColor>
                        <R>255</R>
                        <G>255</G>
                        <B>255</B>
                        <A>255</A>
                        <PackedValue>4294967295</PackedValue>
                    </TintColor>
                    <FlipHorizontally>false</FlipHorizontally>
                    <FlipVertically>false</FlipVertically>
                    <texture_filename>whitedot.png</texture_filename>
                    <asset_name>whitedot</asset_name>
                    <Origin>
                        <X>0.5</X>
                        <Y>0.5</Y>
                    </Origin>
                </Item>
                <Item xsi:type="TextureItem" Name="Texture_2278" Visible="true">
                    <Position>
                        <X>-940</X>
                        <Y>-548</Y>
                    </Position>
                    <CustomProperties />
                    <Rotation>-0.09395033</Rotation>
                    <Scale>
                        <X>127.654816</X>
                        <Y>176.745544</Y>
                    </Scale>
                    <TintColor>
                        <R>255</R>
                        <G>255</G>
                        <B>255</B>
                        <A>255</A>
                        <PackedValue>4294967295</PackedValue>
                    </TintColor>
                    <FlipHorizontally>false</FlipHorizontally>
                    <FlipVertically>false</FlipVertically>
                    <texture_filename>whitedot.png</texture_filename>
                    <asset_name>whitedot</asset_name>
                    <Origin>
                        <X>0.5</X>
                        <Y>0.5</Y>
                    </Origin>
                </Item>
                <Item xsi:type="TextureItem" Name="Texture_2279" Visible="true">
                    <Position>
                        <X>-953</X>
                        <Y>-397</Y>
                    </Position>
                    <CustomProperties />
                    <Rotation>0.262444079</Rotation>
                    <Scale>
                        <X>127.654816</X>
                        <Y>176.745544</Y>
                    </Scale>
                    <TintColor>
                        <R>255</R>
                        <G>255</G>
                        <B>255</B>
                        <A>255</A>
                        <PackedValue>4294967295</PackedValue>
                    </TintColor>
                    <FlipHorizontally>false</FlipHorizontally>
                    <FlipVertically>false</FlipVertically>
                    <texture_filename>whitedot.png</texture_filename>
                    <asset_name>whitedot</asset_name>
                    <Origin>
                        <X>0.5</X>
                        <Y>0.5</Y>
                    </Origin>
                </Item>
                <Item xsi:type="TextureItem" Name="Texture_2280" Visible="true">
                    <Position>
                        <X>-966</X>
                        <Y>-285</Y>
                    </Position>
                    <CustomProperties />
                    <Rotation>-0.0644441247</Rotation>
                    <Scale>
                        <X>127.654816</X>
                        <Y>176.745544</Y>
                    </Scale>
                    <TintColor>
                        <R>255</R>
                        <G>255</G>
                        <B>255</B>
                        <A>255</A>
                        <PackedValue>4294967295</PackedValue>
                    </TintColor>
                    <FlipHorizontally>false</FlipHorizontally>
                    <FlipVertically>false</FlipVertically>
                    <texture_filename>whitedot.png</texture_filename>
                    <asset_name>whitedot</asset_name>
                    <Origin>
                        <X>0.5</X>
                        <Y>0.5</Y>
                    </Origin>
                </Item>
                <Item xsi:type="TextureItem" Name="Texture_2281" Visible="true">
                    <Position>
                        <X>-979</X>
                        <Y>-129</Y>
                    </Position>
                    <CustomProperties />
                    <Rotation>0.222919166</Rotation>
                    <Scale>
                        <X>127.654816</X>
                        <Y>176.745544</Y>
                    </Scale>
                    <TintColor>
                        <R>255</R>
                        <G>255</G>
                        <B>255</B>
                        <A>255</A>
                        <PackedValue>4294967295</PackedValue>
                    </TintColor>
                    <FlipHorizontally>false</FlipHorizontally>
                    <FlipVertically>false</FlipVertically>
                    <texture_filename>whitedot.png</texture_filename>
                    <asset_name>whitedot</asset_name>
                    <Origin>
                        <X>0.5</X>
                        <Y>0.5</Y>
                    </Origin>
                </Item>
                <Item xsi:type="TextureItem" Name="Texture_2282" Visible="true">
                    <Position>
                        <X>-950</X>
                        <Y>-27</Y>
                    </Position>
                    <CustomProperties />
                    <Rotation>-0.3118319</Rotation>
                    <Scale>
                        <X>127.654816</X>
                        <Y>176.745544</Y>
                    </Scale>
                    <TintColor>
                        <R>255</R>
                        <G>255</G>
                        <B>255</B>
                        <A>255</A>
                        <PackedValue>4294967295</PackedValue>
                    </TintColor>
                    <FlipHorizontally>false</FlipHorizontally>
                    <FlipVertically>false</FlipVertically>
                    <texture_filename>whitedot.png</texture_filename>
                    <asset_name>whitedot</asset_name>
                    <Origin>
                        <X>0.5</X>
                        <Y>0.5</Y>
                    </Origin>
                </Item>
            </Items>
            <ScrollSpeed>
                <X>1</X>
                <Y>1</Y>
            </ScrollSpeed>
            <CustomProperties>
                <Property Name="TileSize" Type="string" Description="100">
                    <string>128</string>
                </Property>
                <Property Name="Texture" Type="string" Description="textures/backgrounds/vesuvius/aboveground">
                    <string />
                </Property>
                <Property Name="LayerDepth" Type="string" Description="1">
                    <string>2</string>
                </Property>
            </CustomProperties>
        </Layer>
        <Layer Name="Fox" Visible="true">
            <Items>
                <Item xsi:type="TextureItem" Name="Texture_2235" Visible="true">
                    <Position>
                        <X>1338</X>
                        <Y>-506</Y>
                    </Position>
                    <CustomProperties />
                    <Rotation>0</Rotation>
                    <Scale>
                        <X>3</X>
                        <Y>3</Y>
                    </Scale>
                    <TintColor>
                        <R>255</R>
                        <G>255</G>
                        <B>255</B>
                        <A>255</A>
                        <PackedValue>4294967295</PackedValue>
                    </TintColor>
                    <FlipHorizontally>false</FlipHorizontally>
                    <FlipVertically>false</FlipVertically>
                    <texture_filename>Sprites\Gem.png</texture_filename>
                    <asset_name>Sprites\Gem</asset_name>
                    <Origin>
                        <X>16</X>
                        <Y>16</Y>
                    </Origin>
                </Item>
                <Item xsi:type="TextureItem" Name="Texture_2254" Visible="true">
                    <Position>
                        <X>1661</X>
                        <Y>-209</Y>
                    </Position>
                    <CustomProperties />
                    <Rotation>0</Rotation>
                    <Scale>
                        <X>3</X>
                        <Y>3</Y>
                    </Scale>
                    <TintColor>
                        <R>255</R>
                        <G>255</G>
                        <B>255</B>
                        <A>255</A>
                        <PackedValue>4294967295</PackedValue>
                    </TintColor>
                    <FlipHorizontally>false</FlipHorizontally>
                    <FlipVertically>false</FlipVertically>
                    <texture_filename>Sprites\Gem.png</texture_filename>
                    <asset_name>Sprites\Gem</asset_name>
                    <Origin>
                        <X>16</X>
                        <Y>16</Y>
                    </Origin>
                </Item>
                <Item xsi:type="TextureItem" Name="Texture_2255" Visible="true">
                    <Position>
                        <X>2103</X>
                        <Y>-46</Y>
                    </Position>
                    <CustomProperties />
                    <Rotation>0</Rotation>
                    <Scale>
                        <X>3</X>
                        <Y>3</Y>
                    </Scale>
                    <TintColor>
                        <R>255</R>
                        <G>255</G>
                        <B>255</B>
                        <A>255</A>
                        <PackedValue>4294967295</PackedValue>
                    </TintColor>
                    <FlipHorizontally>false</FlipHorizontally>
                    <FlipVertically>false</FlipVertically>
                    <texture_filename>Sprites\Gem.png</texture_filename>
                    <asset_name>Sprites\Gem</asset_name>
                    <Origin>
                        <X>16</X>
                        <Y>16</Y>
                    </Origin>
                </Item>
                <Item xsi:type="TextureItem" Name="Texture_2290" Visible="true">
                    <Position>
                        <X>-188</X>
                        <Y>-308</Y>
                    </Position>
                    <CustomProperties />
                    <Rotation>0.08229506</Rotation>
                    <Scale>
                        <X>3</X>
                        <Y>3</Y>
                    </Scale>
                    <TintColor>
                        <R>255</R>
                        <G>255</G>
                        <B>255</B>
                        <A>255</A>
                        <PackedValue>4294967295</PackedValue>
                    </TintColor>
                    <FlipHorizontally>false</FlipHorizontally>
                    <FlipVertically>false</FlipVertically>
                    <texture_filename>Sprites\Gem.png</texture_filename>
                    <asset_name>Sprites\Gem</asset_name>
                    <Origin>
                        <X>16</X>
                        <Y>16</Y>
                    </Origin>
                </Item>
                <Item xsi:type="TextureItem" Name="Texture_2291" Visible="true">
                    <Position>
                        <X>-646</X>
                        <Y>-54</Y>
                    </Position>
                    <CustomProperties />
                    <Rotation>0.0065241456</Rotation>
                    <Scale>
                        <X>3</X>
                        <Y>3</Y>
                    </Scale>
                    <TintColor>
                        <R>255</R>
                        <G>255</G>
                        <B>255</B>
                        <A>255</A>
                        <PackedValue>4294967295</PackedValue>
                    </TintColor>
                    <FlipHorizontally>false</FlipHorizontally>
                    <FlipVertically>false</FlipVertically>
                    <texture_filename>Sprites\Gem.png</texture_filename>
                    <asset_name>Sprites\Gem</asset_name>
                    <Origin>
                        <X>16</X>
                        <Y>16</Y>
                    </Origin>
                </Item>
                <Item xsi:type="TextureItem" Name="Texture_2292" Visible="true">
                    <Position>
                        <X>-482</X>
                        <Y>-124</Y>
                    </Position>
                    <CustomProperties />
                    <Rotation>-0.536344647</Rotation>
                    <Scale>
                        <X>3</X>
                        <Y>3</Y>
                    </Scale>
                    <TintColor>
                        <R>255</R>
                        <G>255</G>
                        <B>255</B>
                        <A>255</A>
                        <PackedValue>4294967295</PackedValue>
                    </TintColor>
                    <FlipHorizontally>false</FlipHorizontally>
                    <FlipVertically>false</FlipVertically>
                    <texture_filename>Sprites\Gem.png</texture_filename>
                    <asset_name>Sprites\Gem</asset_name>
                    <Origin>
                        <X>16</X>
                        <Y>16</Y>
                    </Origin>
                </Item>
                <Item xsi:type="TextureItem" Name="Texture_2293" Visible="true">
                    <Position>
                        <X>46</X>
                        <Y>-378</Y>
                    </Position>
                    <CustomProperties />
                    <Rotation>-0.7967579</Rotation>
                    <Scale>
                        <X>3</X>
                        <Y>3</Y>
                    </Scale>
                    <TintColor>
                        <R>255</R>
                        <G>255</G>
                        <B>255</B>
                        <A>255</A>
                        <PackedValue>4294967295</PackedValue>
                    </TintColor>
                    <FlipHorizontally>false</FlipHorizontally>
                    <FlipVertically>false</FlipVertically>
                    <texture_filename>Sprites\Gem.png</texture_filename>
                    <asset_name>Sprites\Gem</asset_name>
                    <Origin>
                        <X>16</X>
                        <Y>16</Y>
                    </Origin>
                </Item>
                <Item xsi:type="TextureItem" Name="Texture_2294" Visible="true">
                    <Position>
                        <X>155</X>
                        <Y>-275</Y>
                    </Position>
                    <CustomProperties />
                    <Rotation>-0.251907617</Rotation>
                    <Scale>
                        <X>3</X>
                        <Y>3</Y>
                    </Scale>
                    <TintColor>
                        <R>255</R>
                        <G>255</G>
                        <B>255</B>
                        <A>255</A>
                        <PackedValue>4294967295</PackedValue>
                    </TintColor>
                    <FlipHorizontally>false</FlipHorizontally>
                    <FlipVertically>false</FlipVertically>
                    <texture_filename>Sprites\Gem.png</texture_filename>
                    <asset_name>Sprites\Gem</asset_name>
                    <Origin>
                        <X>16</X>
                        <Y>16</Y>
                    </Origin>
                </Item>
                <Item xsi:type="TextureItem" Name="Texture_2299" Visible="true">
                    <Position>
                        <X>428</X>
                        <Y>-450</Y>
                    </Position>
                    <CustomProperties />
                    <Rotation>0.659409165</Rotation>
                    <Scale>
                        <X>3</X>
                        <Y>3</Y>
                    </Scale>
                    <TintColor>
                        <R>255</R>
                        <G>255</G>
                        <B>255</B>
                        <A>255</A>
                        <PackedValue>4294967295</PackedValue>
                    </TintColor>
                    <FlipHorizontally>false</FlipHorizontally>
                    <FlipVertically>false</FlipVertically>
                    <texture_filename>Sprites\Gem.png</texture_filename>
                    <asset_name>Sprites\Gem</asset_name>
                    <Origin>
                        <X>16</X>
                        <Y>16</Y>
                    </Origin>
                </Item>
            </Items>
            <ScrollSpeed>
                <X>1</X>
                <Y>1</Y>
            </ScrollSpeed>
            <CustomProperties />
        </Layer>
        <Layer Name="StartPos" Visible="true">
            <Items>
                <Item xsi:type="TextureItem" Name="Texture_0068" Visible="true">
                    <Position>
                        <X>-792</X>
                        <Y>-954</Y>
                    </Position>
                    <CustomProperties />
                    <Rotation>0</Rotation>
                    <Scale>
                        <X>0.6307254</X>
                        <Y>0.6307254</Y>
                    </Scale>
                    <TintColor>
                        <R>255</R>
                        <G>255</G>
                        <B>255</B>
                        <A>255</A>
                        <PackedValue>4294967295</PackedValue>
                    </TintColor>
                    <FlipHorizontally>false</FlipHorizontally>
                    <FlipVertically>false</FlipVertically>
                    <texture_filename>Physical\crate.jpg</texture_filename>
                    <asset_name>Physical\crate</asset_name>
                    <Origin>
                        <X>150</X>
                        <Y>150</Y>
                    </Origin>
                </Item>
            </Items>
            <ScrollSpeed>
                <X>1</X>
                <Y>1</Y>
            </ScrollSpeed>
            <CustomProperties />
        </Layer>
        <Layer Name="RigidBreakableBodies" Visible="true">
            <Items>
                <Item xsi:type="TextureItem" Name="Texture_2284" Visible="true">
                    <Position>
                        <X>219</X>
                        <Y>-372</Y>
                    </Position>
                    <CustomProperties />
                    <Rotation>-0.311203122</Rotation>
                    <Scale>
                        <X>2.3782804</X>
                        <Y>2.3782804</Y>
                    </Scale>
                    <TintColor>
                        <R>255</R>
                        <G>255</G>
                        <B>255</B>
                        <A>255</A>
                        <PackedValue>4294967295</PackedValue>
                    </TintColor>
                    <FlipHorizontally>false</FlipHorizontally>
                    <FlipVertically>false</FlipVertically>
                    <texture_filename>Physical\wood.png</texture_filename>
                    <asset_name>Physical\wood</asset_name>
                    <Origin>
                        <X>10</X>
                        <Y>50</Y>
                    </Origin>
                </Item>
                <Item xsi:type="TextureItem" Name="Texture_2285" Visible="true">
                    <Position>
                        <X>84</X>
                        <Y>-312</Y>
                    </Position>
                    <CustomProperties />
                    <Rotation>0.7842988</Rotation>
                    <Scale>
                        <X>2.3782804</X>
                        <Y>2.3782804</Y>
                    </Scale>
                    <TintColor>
                        <R>255</R>
                        <G>255</G>
                        <B>255</B>
                        <A>255</A>
                        <PackedValue>4294967295</PackedValue>
                    </TintColor>
                    <FlipHorizontally>false</FlipHorizontally>
                    <FlipVertically>false</FlipVertically>
                    <texture_filename>Physical\wood.png</texture_filename>
                    <asset_name>Physical\wood</asset_name>
                    <Origin>
                        <X>10</X>
                        <Y>50</Y>
                    </Origin>
                </Item>
                <Item xsi:type="TextureItem" Name="Texture_2286" Visible="true">
                    <Position>
                        <X>-63</X>
                        <Y>-322</Y>
                    </Position>
                    <CustomProperties />
                    <Rotation>-0.0486520231</Rotation>
                    <Scale>
                        <X>4</X>
                        <Y>2.3782804</Y>
                    </Scale>
                    <TintColor>
                        <R>255</R>
                        <G>255</G>
                        <B>255</B>
                        <A>255</A>
                        <PackedValue>4294967295</PackedValue>
                    </TintColor>
                    <FlipHorizontally>false</FlipHorizontally>
                    <FlipVertically>false</FlipVertically>
                    <texture_filename>Physical\wood.png</texture_filename>
                    <asset_name>Physical\wood</asset_name>
                    <Origin>
                        <X>10</X>
                        <Y>50</Y>
                    </Origin>
                </Item>
                <Item xsi:type="TextureItem" Name="Texture_2287" Visible="true">
                    <Position>
                        <X>-572</X>
                        <Y>-119</Y>
                    </Position>
                    <CustomProperties />
                    <Rotation>0</Rotation>
                    <Scale>
                        <X>2.3782804</X>
                        <Y>2.3782804</Y>
                    </Scale>
                    <TintColor>
                        <R>255</R>
                        <G>255</G>
                        <B>255</B>
                        <A>255</A>
                        <PackedValue>4294967295</PackedValue>
                    </TintColor>
                    <FlipHorizontally>false</FlipHorizontally>
                    <FlipVertically>false</FlipVertically>
                    <texture_filename>Physical\wood.png</texture_filename>
                    <asset_name>Physical\wood</asset_name>
                    <Origin>
                        <X>10</X>
                        <Y>50</Y>
                    </Origin>
                </Item>
                <Item xsi:type="TextureItem" Name="Texture_2288" Visible="true">
                    <Position>
                        <X>-364</X>
                        <Y>-248</Y>
                    </Position>
                    <CustomProperties />
                    <Rotation>-1.48057461</Rotation>
                    <Scale>
                        <X>2.3782804</X>
                        <Y>5</Y>
                    </Scale>
                    <TintColor>
                        <R>255</R>
                        <G>255</G>
                        <B>255</B>
                        <A>255</A>
                        <PackedValue>4294967295</PackedValue>
                    </TintColor>
                    <FlipHorizontally>false</FlipHorizontally>
                    <FlipVertically>false</FlipVertically>
                    <texture_filename>Physical\wood.png</texture_filename>
                    <asset_name>Physical\wood</asset_name>
                    <Origin>
                        <X>10</X>
                        <Y>50</Y>
                    </Origin>
                </Item>
                <Item xsi:type="TextureItem" Name="Texture_2289" Visible="true">
                    <Position>
                        <X>25</X>
                        <Y>-486</Y>
                    </Position>
                    <CustomProperties />
                    <Rotation>-1.729749</Rotation>
                    <Scale>
                        <X>2.3782804</X>
                        <Y>3</Y>
                    </Scale>
                    <TintColor>
                        <R>255</R>
                        <G>255</G>
                        <B>255</B>
                        <A>255</A>
                        <PackedValue>4294967295</PackedValue>
                    </TintColor>
                    <FlipHorizontally>false</FlipHorizontally>
                    <FlipVertically>false</FlipVertically>
                    <texture_filename>Physical\wood.png</texture_filename>
                    <asset_name>Physical\wood</asset_name>
                    <Origin>
                        <X>10</X>
                        <Y>50</Y>
                    </Origin>
                </Item>
                <Item xsi:type="TextureItem" Name="Texture_2295" Visible="true">
                    <Position>
                        <X>304</X>
                        <Y>-453</Y>
                    </Position>
                    <CustomProperties />
                    <Rotation>-7.19061661</Rotation>
                    <Scale>
                        <X>2.3782804</X>
                        <Y>3</Y>
                    </Scale>
                    <TintColor>
                        <R>255</R>
                        <G>255</G>
                        <B>255</B>
                        <A>255</A>
                        <PackedValue>4294967295</PackedValue>
                    </TintColor>
                    <FlipHorizontally>false</FlipHorizontally>
                    <FlipVertically>false</FlipVertically>
                    <texture_filename>Physical\wood.png</texture_filename>
                    <asset_name>Physical\wood</asset_name>
                    <Origin>
                        <X>10</X>
                        <Y>50</Y>
                    </Origin>
                </Item>
                <Item xsi:type="TextureItem" Name="Texture_2296" Visible="true">
                    <Position>
                        <X>-256</X>
                        <Y>-371</Y>
                    </Position>
                    <CustomProperties />
                    <Rotation>-2.13699722</Rotation>
                    <Scale>
                        <X>2.3782804</X>
                        <Y>3</Y>
                    </Scale>
                    <TintColor>
                        <R>255</R>
                        <G>255</G>
                        <B>255</B>
                        <A>255</A>
                        <PackedValue>4294967295</PackedValue>
                    </TintColor>
                    <FlipHorizontally>false</FlipHorizontally>
                    <FlipVertically>false</FlipVertically>
                    <texture_filename>Physical\wood.png</texture_filename>
                    <asset_name>Physical\wood</asset_name>
                    <Origin>
                        <X>10</X>
                        <Y>50</Y>
                    </Origin>
                </Item>
                <Item xsi:type="TextureItem" Name="Texture_2297" Visible="true">
                    <Position>
                        <X>400</X>
                        <Y>-590</Y>
                    </Position>
                    <CustomProperties />
                    <Rotation>-1.5761528</Rotation>
                    <Scale>
                        <X>2.3782804</X>
                        <Y>4.2</Y>
                    </Scale>
                    <TintColor>
                        <R>255</R>
                        <G>255</G>
                        <B>255</B>
                        <A>255</A>
                        <PackedValue>4294967295</PackedValue>
                    </TintColor>
                    <FlipHorizontally>false</FlipHorizontally>
                    <FlipVertically>false</FlipVertically>
                    <texture_filename>Physical\wood.png</texture_filename>
                    <asset_name>Physical\wood</asset_name>
                    <Origin>
                        <X>10</X>
                        <Y>50</Y>
                    </Origin>
                </Item>
                <Item xsi:type="TextureItem" Name="Texture_2300" Visible="true">
                    <Position>
                        <X>939</X>
                        <Y>-814</Y>
                    </Position>
                    <CustomProperties />
                    <Rotation>0</Rotation>
                    <Scale>
                        <X>1.83959377</X>
                        <Y>1.83959377</Y>
                    </Scale>
                    <TintColor>
                        <R>255</R>
                        <G>255</G>
                        <B>255</B>
                        <A>255</A>
                        <PackedValue>4294967295</PackedValue>
                    </TintColor>
                    <FlipHorizontally>false</FlipHorizontally>
                    <FlipVertically>false</FlipVertically>
                    <texture_filename>Physical\wood.png</texture_filename>
                    <asset_name>Physical\wood</asset_name>
                    <Origin>
                        <X>10</X>
                        <Y>50</Y>
                    </Origin>
                </Item>
                <Item xsi:type="TextureItem" Name="Texture_2301" Visible="true">
                    <Position>
                        <X>330</X>
                        <Y>-319</Y>
                    </Position>
                    <CustomProperties />
                    <Rotation>0.934993744</Rotation>
                    <Scale>
                        <X>2.07529068</X>
                        <Y>1.216435</Y>
                    </Scale>
                    <TintColor>
                        <R>255</R>
                        <G>255</G>
                        <B>255</B>
                        <A>255</A>
                        <PackedValue>4294967295</PackedValue>
                    </TintColor>
                    <FlipHorizontally>false</FlipHorizontally>
                    <FlipVertically>false</FlipVertically>
                    <texture_filename>Physical\wood.png</texture_filename>
                    <asset_name>Physical\wood</asset_name>
                    <Origin>
                        <X>10</X>
                        <Y>50</Y>
                    </Origin>
                </Item>
            </Items>
            <ScrollSpeed>
                <X>1</X>
                <Y>1</Y>
            </ScrollSpeed>
            <CustomProperties>
                <Property Name="Mass" Type="string" Description="5">
                    <string>100</string>
                </Property>
                <Property Name="Type" Type="string" Description="Circle">
                    <string>Circle</string>
                </Property>
                <Property Name="LayerDepth" Type="string" Description="0">
                    <string>0</string>
                </Property>
                <Property Name="Friction" Type="string" Description="">
                    <string>10</string>
                </Property>
            </CustomProperties>
        </Layer>
        <Layer Name="TNT" Visible="true">
            <Items />
            <ScrollSpeed>
                <X>1</X>
                <Y>1</Y>
            </ScrollSpeed>
            <CustomProperties />
        </Layer>
        <Layer Name="RigidBodies" Visible="true">
            <Items />
            <ScrollSpeed>
                <X>1</X>
                <Y>1</Y>
            </ScrollSpeed>
            <CustomProperties>
                <Property Name="Mass" Type="string" Description="">
                    <string>100</string>
                </Property>
                <Property Name="Type" Type="string" Description="">
                    <string>Circle</string>
                </Property>
            </CustomProperties>
        </Layer>
        <Layer Name="Sprite#2" Visible="true">
            <Items>
                <Item xsi:type="TextureItem" Name="Texture_2302" Visible="true">
                    <Position>
                        <X>868</X>
                        <Y>-773</Y>
                    </Position>
                    <CustomProperties />
                    <Rotation>0</Rotation>
                    <Scale>
                        <X>1</X>
                        <Y>1</Y>
                    </Scale>
                    <TintColor>
                        <R>255</R>
                        <G>255</G>
                        <B>255</B>
                        <A>255</A>
                        <PackedValue>4294967295</PackedValue>
                    </TintColor>
                    <FlipHorizontally>false</FlipHorizontally>
                    <FlipVertically>false</FlipVertically>
                    <texture_filename>tyre.png</texture_filename>
                    <asset_name>tyre</asset_name>
                    <Origin>
                        <X>50</X>
                        <Y>50</Y>
                    </Origin>
                </Item>
                <Item xsi:type="TextureItem" Name="Texture_2303" Visible="true">
                    <Position>
                        <X>1012</X>
                        <Y>-773</Y>
                    </Position>
                    <CustomProperties />
                    <Rotation>0</Rotation>
                    <Scale>
                        <X>1</X>
                        <Y>1</Y>
                    </Scale>
                    <TintColor>
                        <R>255</R>
                        <G>255</G>
                        <B>255</B>
                        <A>255</A>
                        <PackedValue>4294967295</PackedValue>
                    </TintColor>
                    <FlipHorizontally>false</FlipHorizontally>
                    <FlipVertically>false</FlipVertically>
                    <texture_filename>tyre.png</texture_filename>
                    <asset_name>tyre</asset_name>
                    <Origin>
                        <X>50</X>
                        <Y>50</Y>
                    </Origin>
                </Item>
                <Item xsi:type="TextureItem" Name="Texture_2304" Visible="true">
                    <Position>
                        <X>939</X>
                        <Y>-948</Y>
                    </Position>
                    <CustomProperties />
                    <Rotation>0</Rotation>
                    <Scale>
                        <X>1</X>
                        <Y>1</Y>
                    </Scale>
                    <TintColor>
                        <R>255</R>
                        <G>255</G>
                        <B>255</B>
                        <A>255</A>
                        <PackedValue>4294967295</PackedValue>
                    </TintColor>
                    <FlipHorizontally>false</FlipHorizontally>
                    <FlipVertically>false</FlipVertically>
                    <texture_filename>donut.png</texture_filename>
                    <asset_name>donut</asset_name>
                    <Origin>
                        <X>30</X>
                        <Y>25</Y>
                    </Origin>
                </Item>
                <Item xsi:type="TextureItem" Name="Texture_2305" Visible="true">
                    <Position>
                        <X>682</X>
                        <Y>-688</Y>
                    </Position>
                    <CustomProperties />
                    <Rotation>0</Rotation>
                    <Scale>
                        <X>1</X>
                        <Y>1</Y>
                    </Scale>
                    <TintColor>
                        <R>255</R>
                        <G>255</G>
                        <B>255</B>
                        <A>255</A>
                        <PackedValue>4294967295</PackedValue>
                    </TintColor>
                    <FlipHorizontally>false</FlipHorizontally>
                    <FlipVertically>false</FlipVertically>
                    <texture_filename>donut.png</texture_filename>
                    <asset_name>donut</asset_name>
                    <Origin>
                        <X>30</X>
                        <Y>25</Y>
                    </Origin>
                </Item>
                <Item xsi:type="TextureItem" Name="Texture_2306" Visible="true">
                    <Position>
                        <X>542</X>
                        <Y>-598</Y>
                    </Position>
                    <CustomProperties />
                    <Rotation>0</Rotation>
                    <Scale>
                        <X>1</X>
                        <Y>1</Y>
                    </Scale>
                    <TintColor>
                        <R>255</R>
                        <G>255</G>
                        <B>255</B>
                        <A>255</A>
                        <PackedValue>4294967295</PackedValue>
                    </TintColor>
                    <FlipHorizontally>false</FlipHorizontally>
                    <FlipVertically>false</FlipVertically>
                    <texture_filename>donut.png</texture_filename>
                    <asset_name>donut</asset_name>
                    <Origin>
                        <X>30</X>
                        <Y>25</Y>
                    </Origin>
                </Item>
                <Item xsi:type="TextureItem" Name="Texture_2307" Visible="true">
                    <Position>
                        <X>1159</X>
                        <Y>-651</Y>
                    </Position>
                    <CustomProperties />
                    <Rotation>0</Rotation>
                    <Scale>
                        <X>1</X>
                        <Y>1</Y>
                    </Scale>
                    <TintColor>
                        <R>255</R>
                        <G>255</G>
                        <B>255</B>
                        <A>255</A>
                        <PackedValue>4294967295</PackedValue>
                    </TintColor>
                    <FlipHorizontally>false</FlipHorizontally>
                    <FlipVertically>false</FlipVertically>
                    <texture_filename>donut.png</texture_filename>
                    <asset_name>donut</asset_name>
                    <Origin>
                        <X>30</X>
                        <Y>25</Y>
                    </Origin>
                </Item>
                <Item xsi:type="TextureItem" Name="Texture_2308" Visible="true">
                    <Position>
                        <X>1512</X>
                        <Y>-375</Y>
                    </Position>
                    <CustomProperties />
                    <Rotation>0</Rotation>
                    <Scale>
                        <X>1</X>
                        <Y>1</Y>
                    </Scale>
                    <TintColor>
                        <R>255</R>
                        <G>255</G>
                        <B>255</B>
                        <A>255</A>
                        <PackedValue>4294967295</PackedValue>
                    </TintColor>
                    <FlipHorizontally>false</FlipHorizontally>
                    <FlipVertically>false</FlipVertically>
                    <texture_filename>donut.png</texture_filename>
                    <asset_name>donut</asset_name>
                    <Origin>
                        <X>30</X>
                        <Y>25</Y>
                    </Origin>
                </Item>
                <Item xsi:type="TextureItem" Name="Texture_2309" Visible="true">
                    <Position>
                        <X>22</X>
                        <Y>-594</Y>
                    </Position>
                    <CustomProperties />
                    <Rotation>-0.153723583</Rotation>
                    <Scale>
                        <X>1</X>
                        <Y>1</Y>
                    </Scale>
                    <TintColor>
                        <R>255</R>
                        <G>255</G>
                        <B>255</B>
                        <A>255</A>
                        <PackedValue>4294967295</PackedValue>
                    </TintColor>
                    <FlipHorizontally>false</FlipHorizontally>
                    <FlipVertically>false</FlipVertically>
                    <texture_filename>donutcase.png</texture_filename>
                    <asset_name>donutcase</asset_name>
                    <Origin>
                        <X>66</X>
                        <Y>81</Y>
                    </Origin>
                </Item>
            </Items>
            <ScrollSpeed>
                <X>1</X>
                <Y>1</Y>
            </ScrollSpeed>
            <CustomProperties>
                <Property Name="LayerDepth" Type="string" Description="">
                    <string>0</string>
                </Property>
            </CustomProperties>
        </Layer>
        <Layer Name="BreakableShapeRigidBodies" Visible="true">
            <Items />
            <ScrollSpeed>
                <X>1</X>
                <Y>1</Y>
            </ScrollSpeed>
            <CustomProperties />
        </Layer>
    </Layers>
    <CustomProperties>
        <Property Name="CamStartPos" Type="Vector2" Description="">
            <Vector2>
                <X>49</X>
                <Y>561</Y>
            </Vector2>
        </Property>
        <Property Name="SpotStartPos" Type="Vector2" Description="">
            <Vector2>
                <X>-383</X>
                <Y>485</Y>
            </Vector2>
        </Property>
        <Property Name="CamStartScale" Type="string" Description="0.1">
            <string>0.35</string>
        </Property>
        <Property Name="MaxGameCamPos" Type="Vector2" Description="">
            <Vector2>
                <X>969</X>
                <Y>460</Y>
            </Vector2>
        </Property>
        <Property Name="ScaleAtMax" Type="string" Description="0.2">
            <string>0.35</string>
        </Property>
        <Property Name="MinCamPos" Type="string" Description="">
            <string>-1500</string>
        </Property>
        <Property Name="MaxCamPos" Type="string" Description="">
            <string>4000</string>
        </Property>
        <Property Name="LeftInvisibleWall" Type="string" Description="">
            <string>-2500</string>
        </Property>
        <Property Name="RightInvisibleWall" Type="string" Description="">
            <string>3000</string>
        </Property>
        <Property Name="MaxCamTarget" Type="string" Description="">
            <string>400</string>
        </Property>
        <Property Name="Chicks" Type="string" Description="">
            <string>1+1+1</string>
        </Property>
        <Property Name="RigidBody" Type="string" Description="">
            <string />
        </Property>
        <Property Name="Sprite#2" Type="string" Description="">
            <string />
        </Property>
        <Property Name="WorldDir" Type="string" Description="">
            <string>Vesuvius</string>
        </Property>
    </CustomProperties>
    <EditorRelated>
        <NextItemNumber>2309</NextItemNumber>
        <ContentRootFolder>C:\mobile\Hen\Hen\HenContent\Textures</ContentRootFolder>
        <CameraPosition>
            <X>57.8950424</X>
            <Y>-525.4945</Y>
        </CameraPosition>
        <Version>1.3.0.0</Version>
    </EditorRelated>
</Level>