<?xml version="1.0"?>
<Level xmlns:xsi="http://www.w3.org/2001/XMLSchema-instance" xmlns:xsd="http://www.w3.org/2001/XMLSchema" Name="Level_01" Visible="true">
    <Layers>
        <Layer Name="Fox" Visible="true">
            <Items>
                <Item xsi:type="TextureItem" Name="Texture_1653" Visible="true">
                    <Position>
                        <X>95</X>
                        <Y>-519</Y>
                    </Position>
                    <CustomProperties />
                    <Rotation>0</Rotation>
                    <Scale>
                        <X>3</X>
                        <Y>3</Y>
                    </Scale>
                    <TintColor>
                        <R>255</R>
                        <G>255</G>
                        <B>255</B>
                        <A>255</A>
                        <PackedValue>4294967295</PackedValue>
                    </TintColor>
                    <FlipHorizontally>false</FlipHorizontally>
                    <FlipVertically>false</FlipVertically>
                    <texture_filename>Sprites\Gem.png</texture_filename>
                    <asset_name>Sprites\Gem</asset_name>
                    <Origin>
                        <X>16</X>
                        <Y>16</Y>
                    </Origin>
                </Item>
                <Item xsi:type="TextureItem" Name="Texture_1805" Visible="true">
                    <Position>
                        <X>553</X>
                        <Y>-519</Y>
                    </Position>
                    <CustomProperties />
                    <Rotation>0</Rotation>
                    <Scale>
                        <X>3</X>
                        <Y>3</Y>
                    </Scale>
                    <TintColor>
                        <R>255</R>
                        <G>255</G>
                        <B>255</B>
                        <A>255</A>
                        <PackedValue>4294967295</PackedValue>
                    </TintColor>
                    <FlipHorizontally>false</FlipHorizontally>
                    <FlipVertically>false</FlipVertically>
                    <texture_filename>Sprites\Gem.png</texture_filename>
                    <asset_name>Sprites\Gem</asset_name>
                    <Origin>
                        <X>16</X>
                        <Y>16</Y>
                    </Origin>
                </Item>
                <Item xsi:type="TextureItem" Name="Texture_1806" Visible="true">
                    <Position>
                        <X>582</X>
                        <Y>-54</Y>
                    </Position>
                    <CustomProperties />
                    <Rotation>0</Rotation>
                    <Scale>
                        <X>3</X>
                        <Y>3</Y>
                    </Scale>
                    <TintColor>
                        <R>255</R>
                        <G>255</G>
                        <B>255</B>
                        <A>255</A>
                        <PackedValue>4294967295</PackedValue>
                    </TintColor>
                    <FlipHorizontally>false</FlipHorizontally>
                    <FlipVertically>false</FlipVertically>
                    <texture_filename>Sprites\Gem.png</texture_filename>
                    <asset_name>Sprites\Gem</asset_name>
                    <Origin>
                        <X>16</X>
                        <Y>16</Y>
                    </Origin>
                </Item>
                <Item xsi:type="TextureItem" Name="Texture_1818" Visible="true">
                    <Position>
                        <X>935</X>
                        <Y>-707</Y>
                    </Position>
                    <CustomProperties />
                    <Rotation>0</Rotation>
                    <Scale>
                        <X>3</X>
                        <Y>3</Y>
                    </Scale>
                    <TintColor>
                        <R>255</R>
                        <G>255</G>
                        <B>255</B>
                        <A>255</A>
                        <PackedValue>4294967295</PackedValue>
                    </TintColor>
                    <FlipHorizontally>false</FlipHorizontally>
                    <FlipVertically>false</FlipVertically>
                    <texture_filename>Sprites\Gem.png</texture_filename>
                    <asset_name>Sprites\Gem</asset_name>
                    <Origin>
                        <X>16</X>
                        <Y>16</Y>
                    </Origin>
                </Item>
            </Items>
            <ScrollSpeed>
                <X>1</X>
                <Y>1</Y>
            </ScrollSpeed>
            <CustomProperties />
        </Layer>
        <Layer Name="Terrain" Visible="true">
            <Items>
                <Item xsi:type="TextureItem" Name="Copy of Texture_0005" Visible="true">
                    <Position>
                        <X>0</X>
                        <Y>131</Y>
                    </Position>
                    <CustomProperties />
                    <Rotation>0</Rotation>
                    <Scale>
                        <X>9920.353</X>
                        <Y>256</Y>
                    </Scale>
                    <TintColor>
                        <R>255</R>
                        <G>255</G>
                        <B>255</B>
                        <A>255</A>
                        <PackedValue>4294967295</PackedValue>
                    </TintColor>
                    <FlipHorizontally>false</FlipHorizontally>
                    <FlipVertically>false</FlipVertically>
                    <texture_filename>whitedot.png</texture_filename>
                    <asset_name>whitedot</asset_name>
                    <Origin>
                        <X>0.5</X>
                        <Y>0.5</Y>
                    </Origin>
                </Item>
                <Item xsi:type="TextureItem" Name="Texture_1835" Visible="true">
                    <Position>
                        <X>382</X>
                        <Y>-1166</Y>
                    </Position>
                    <CustomProperties />
                    <Rotation>0</Rotation>
                    <Scale>
                        <X>100</X>
                        <Y>30</Y>
                    </Scale>
                    <TintColor>
                        <R>255</R>
                        <G>255</G>
                        <B>255</B>
                        <A>255</A>
                        <PackedValue>4294967295</PackedValue>
                    </TintColor>
                    <FlipHorizontally>false</FlipHorizontally>
                    <FlipVertically>false</FlipVertically>
                    <texture_filename>whitedot.png</texture_filename>
                    <asset_name>whitedot</asset_name>
                    <Origin>
                        <X>0.5</X>
                        <Y>0.5</Y>
                    </Origin>
                </Item>
                <Item xsi:type="TextureItem" Name="Texture_1836" Visible="true">
                    <Position>
                        <X>749</X>
                        <Y>-1166</Y>
                    </Position>
                    <CustomProperties />
                    <Rotation>0</Rotation>
                    <Scale>
                        <X>100</X>
                        <Y>30</Y>
                    </Scale>
                    <TintColor>
                        <R>255</R>
                        <G>255</G>
                        <B>255</B>
                        <A>255</A>
                        <PackedValue>4294967295</PackedValue>
                    </TintColor>
                    <FlipHorizontally>false</FlipHorizontally>
                    <FlipVertically>false</FlipVertically>
                    <texture_filename>whitedot.png</texture_filename>
                    <asset_name>whitedot</asset_name>
                    <Origin>
                        <X>0.5</X>
                        <Y>0.5</Y>
                    </Origin>
                </Item>
                <Item xsi:type="TextureItem" Name="Texture_1843" Visible="true">
                    <Position>
                        <X>345</X>
                        <Y>-1218</Y>
                    </Position>
                    <CustomProperties />
                    <Rotation>0</Rotation>
                    <Scale>
                        <X>30</X>
                        <Y>100</Y>
                    </Scale>
                    <TintColor>
                        <R>255</R>
                        <G>255</G>
                        <B>255</B>
                        <A>255</A>
                        <PackedValue>4294967295</PackedValue>
                    </TintColor>
                    <FlipHorizontally>false</FlipHorizontally>
                    <FlipVertically>false</FlipVertically>
                    <texture_filename>whitedot.png</texture_filename>
                    <asset_name>whitedot</asset_name>
                    <Origin>
                        <X>0.5</X>
                        <Y>0.5</Y>
                    </Origin>
                </Item>
                <Item xsi:type="TextureItem" Name="Texture_1844" Visible="true">
                    <Position>
                        <X>780</X>
                        <Y>-1225</Y>
                    </Position>
                    <CustomProperties />
                    <Rotation>0</Rotation>
                    <Scale>
                        <X>30</X>
                        <Y>100</Y>
                    </Scale>
                    <TintColor>
                        <R>255</R>
                        <G>255</G>
                        <B>255</B>
                        <A>255</A>
                        <PackedValue>4294967295</PackedValue>
                    </TintColor>
                    <FlipHorizontally>false</FlipHorizontally>
                    <FlipVertically>false</FlipVertically>
                    <texture_filename>whitedot.png</texture_filename>
                    <asset_name>whitedot</asset_name>
                    <Origin>
                        <X>0.5</X>
                        <Y>0.5</Y>
                    </Origin>
                </Item>
                <Item xsi:type="TextureItem" Name="Texture_1848" Visible="true">
                    <Position>
                        <X>-1746</X>
                        <Y>-53</Y>
                    </Position>
                    <CustomProperties />
                    <Rotation>0</Rotation>
                    <Scale>
                        <X>583.7355</X>
                        <Y>583.7355</Y>
                    </Scale>
                    <TintColor>
                        <R>255</R>
                        <G>255</G>
                        <B>255</B>
                        <A>255</A>
                        <PackedValue>4294967295</PackedValue>
                    </TintColor>
                    <FlipHorizontally>false</FlipHorizontally>
                    <FlipVertically>false</FlipVertically>
                    <texture_filename>whitedot.png</texture_filename>
                    <asset_name>whitedot</asset_name>
                    <Origin>
                        <X>0.5</X>
                        <Y>0.5</Y>
                    </Origin>
                </Item>
            </Items>
            <ScrollSpeed>
                <X>1</X>
                <Y>1</Y>
            </ScrollSpeed>
            <CustomProperties>
                <Property Name="TileSize" Type="string" Description="100">
                    <string>128</string>
                </Property>
                <Property Name="Texture" Type="string" Description="textures/backgrounds/paris/aboveground">
                    <string />
                </Property>
                <Property Name="LayerDepth" Type="string" Description="1">
                    <string>2</string>
                </Property>
            </CustomProperties>
        </Layer>
        <Layer Name="StartPos" Visible="true">
            <Items>
                <Item xsi:type="TextureItem" Name="Texture_0068" Visible="true">
                    <Position>
                        <X>-1548</X>
                        <Y>-438</Y>
                    </Position>
                    <CustomProperties />
                    <Rotation>0</Rotation>
                    <Scale>
                        <X>0.640921831</X>
                        <Y>0.640921831</Y>
                    </Scale>
                    <TintColor>
                        <R>255</R>
                        <G>255</G>
                        <B>255</B>
                        <A>255</A>
                        <PackedValue>4294967295</PackedValue>
                    </TintColor>
                    <FlipHorizontally>false</FlipHorizontally>
                    <FlipVertically>false</FlipVertically>
                    <texture_filename>Physical\crate.jpg</texture_filename>
                    <asset_name>Physical\crate</asset_name>
                    <Origin>
                        <X>150</X>
                        <Y>150</Y>
                    </Origin>
                </Item>
            </Items>
            <ScrollSpeed>
                <X>1</X>
                <Y>1</Y>
            </ScrollSpeed>
            <CustomProperties />
        </Layer>
        <Layer Name="RigidBreakableBodies" Visible="true">
            <Items>
                <Item xsi:type="TextureItem" Name="Texture_1785" Visible="true">
                    <Position>
                        <X>-195</X>
                        <Y>-162</Y>
                    </Position>
                    <CustomProperties />
                    <Rotation>0</Rotation>
                    <Scale>
                        <X>3.21105814</X>
                        <Y>3.21105814</Y>
                    </Scale>
                    <TintColor>
                        <R>255</R>
                        <G>255</G>
                        <B>255</B>
                        <A>255</A>
                        <PackedValue>4294967295</PackedValue>
                    </TintColor>
                    <FlipHorizontally>false</FlipHorizontally>
                    <FlipVertically>false</FlipVertically>
                    <texture_filename>Physical\cement.png</texture_filename>
                    <asset_name>Physical\cement</asset_name>
                    <Origin>
                        <X>10</X>
                        <Y>50</Y>
                    </Origin>
                </Item>
                <Item xsi:type="TextureItem" Name="Texture_1786" Visible="true">
                    <Position>
                        <X>107</X>
                        <Y>-160</Y>
                    </Position>
                    <CustomProperties />
                    <Rotation>0</Rotation>
                    <Scale>
                        <X>3.21105814</X>
                        <Y>3.21105814</Y>
                    </Scale>
                    <TintColor>
                        <R>255</R>
                        <G>255</G>
                        <B>255</B>
                        <A>255</A>
                        <PackedValue>4294967295</PackedValue>
                    </TintColor>
                    <FlipHorizontally>false</FlipHorizontally>
                    <FlipVertically>false</FlipVertically>
                    <texture_filename>Physical\cement.png</texture_filename>
                    <asset_name>Physical\cement</asset_name>
                    <Origin>
                        <X>10</X>
                        <Y>50</Y>
                    </Origin>
                </Item>
                <Item xsi:type="TextureItem" Name="Texture_1790" Visible="true">
                    <Position>
                        <X>-63</X>
                        <Y>-358</Y>
                    </Position>
                    <CustomProperties />
                    <Rotation>-1.57212389</Rotation>
                    <Scale>
                        <X>3.21105814</X>
                        <Y>3.21105814</Y>
                    </Scale>
                    <TintColor>
                        <R>255</R>
                        <G>255</G>
                        <B>255</B>
                        <A>255</A>
                        <PackedValue>4294967295</PackedValue>
                    </TintColor>
                    <FlipHorizontally>false</FlipHorizontally>
                    <FlipVertically>false</FlipVertically>
                    <texture_filename>Physical\cement.png</texture_filename>
                    <asset_name>Physical\cement</asset_name>
                    <Origin>
                        <X>10</X>
                        <Y>50</Y>
                    </Origin>
                </Item>
                <Item xsi:type="TextureItem" Name="Texture_1791" Visible="true">
                    <Position>
                        <X>261</X>
                        <Y>-358</Y>
                    </Position>
                    <CustomProperties />
                    <Rotation>-1.57212389</Rotation>
                    <Scale>
                        <X>3.21105814</X>
                        <Y>3.21105814</Y>
                    </Scale>
                    <TintColor>
                        <R>255</R>
                        <G>255</G>
                        <B>255</B>
                        <A>255</A>
                        <PackedValue>4294967295</PackedValue>
                    </TintColor>
                    <FlipHorizontally>false</FlipHorizontally>
                    <FlipVertically>false</FlipVertically>
                    <texture_filename>Physical\cement.png</texture_filename>
                    <asset_name>Physical\cement</asset_name>
                    <Origin>
                        <X>10</X>
                        <Y>50</Y>
                    </Origin>
                </Item>
                <Item xsi:type="TextureItem" Name="Texture_1793" Visible="true">
                    <Position>
                        <X>466</X>
                        <Y>-162</Y>
                    </Position>
                    <CustomProperties />
                    <Rotation>0</Rotation>
                    <Scale>
                        <X>3.21105814</X>
                        <Y>3.21105814</Y>
                    </Scale>
                    <TintColor>
                        <R>255</R>
                        <G>255</G>
                        <B>255</B>
                        <A>255</A>
                        <PackedValue>4294967295</PackedValue>
                    </TintColor>
                    <FlipHorizontally>false</FlipHorizontally>
                    <FlipVertically>false</FlipVertically>
                    <texture_filename>Physical\wood.png</texture_filename>
                    <asset_name>Physical\wood</asset_name>
                    <Origin>
                        <X>10</X>
                        <Y>50</Y>
                    </Origin>
                </Item>
                <Item xsi:type="TextureItem" Name="Texture_1794" Visible="true">
                    <Position>
                        <X>341</X>
                        <Y>-80</Y>
                    </Position>
                    <CustomProperties />
                    <Rotation>0</Rotation>
                    <Scale>
                        <X>9</X>
                        <Y>1.65</Y>
                    </Scale>
                    <TintColor>
                        <R>255</R>
                        <G>255</G>
                        <B>255</B>
                        <A>255</A>
                        <PackedValue>4294967295</PackedValue>
                    </TintColor>
                    <FlipHorizontally>false</FlipHorizontally>
                    <FlipVertically>false</FlipVertically>
                    <texture_filename>Physical\cement.png</texture_filename>
                    <asset_name>Physical\cement</asset_name>
                    <Origin>
                        <X>10</X>
                        <Y>50</Y>
                    </Origin>
                </Item>
                <Item xsi:type="TextureItem" Name="Texture_1795" Visible="true">
                    <Position>
                        <X>343</X>
                        <Y>-244</Y>
                    </Position>
                    <CustomProperties />
                    <Rotation>0</Rotation>
                    <Scale>
                        <X>9</X>
                        <Y>1.65</Y>
                    </Scale>
                    <TintColor>
                        <R>255</R>
                        <G>255</G>
                        <B>255</B>
                        <A>255</A>
                        <PackedValue>4294967295</PackedValue>
                    </TintColor>
                    <FlipHorizontally>false</FlipHorizontally>
                    <FlipVertically>false</FlipVertically>
                    <texture_filename>Physical\cement.png</texture_filename>
                    <asset_name>Physical\cement</asset_name>
                    <Origin>
                        <X>10</X>
                        <Y>50</Y>
                    </Origin>
                </Item>
                <Item xsi:type="TextureItem" Name="Texture_1796" Visible="true">
                    <Position>
                        <X>591</X>
                        <Y>-362</Y>
                    </Position>
                    <CustomProperties />
                    <Rotation>-1.57212389</Rotation>
                    <Scale>
                        <X>3.21105814</X>
                        <Y>3.21105814</Y>
                    </Scale>
                    <TintColor>
                        <R>255</R>
                        <G>255</G>
                        <B>255</B>
                        <A>255</A>
                        <PackedValue>4294967295</PackedValue>
                    </TintColor>
                    <FlipHorizontally>false</FlipHorizontally>
                    <FlipVertically>false</FlipVertically>
                    <texture_filename>Physical\cement.png</texture_filename>
                    <asset_name>Physical\cement</asset_name>
                    <Origin>
                        <X>10</X>
                        <Y>50</Y>
                    </Origin>
                </Item>
                <Item xsi:type="TextureItem" Name="Texture_1797" Visible="true">
                    <Position>
                        <X>718</X>
                        <Y>-162</Y>
                    </Position>
                    <CustomProperties />
                    <Rotation>0</Rotation>
                    <Scale>
                        <X>3.21105814</X>
                        <Y>3.21105814</Y>
                    </Scale>
                    <TintColor>
                        <R>255</R>
                        <G>255</G>
                        <B>255</B>
                        <A>255</A>
                        <PackedValue>4294967295</PackedValue>
                    </TintColor>
                    <FlipHorizontally>false</FlipHorizontally>
                    <FlipVertically>false</FlipVertically>
                    <texture_filename>Physical\wood.png</texture_filename>
                    <asset_name>Physical\wood</asset_name>
                    <Origin>
                        <X>10</X>
                        <Y>50</Y>
                    </Origin>
                </Item>
                <Item xsi:type="TextureItem" Name="Texture_1798" Visible="true">
                    <Position>
                        <X>483</X>
                        <Y>-426</Y>
                    </Position>
                    <CustomProperties />
                    <Rotation>-1.57212389</Rotation>
                    <Scale>
                        <X>3.21105814</X>
                        <Y>3.21105814</Y>
                    </Scale>
                    <TintColor>
                        <R>255</R>
                        <G>255</G>
                        <B>255</B>
                        <A>255</A>
                        <PackedValue>4294967295</PackedValue>
                    </TintColor>
                    <FlipHorizontally>false</FlipHorizontally>
                    <FlipVertically>false</FlipVertically>
                    <texture_filename>Physical\cement.png</texture_filename>
                    <asset_name>Physical\cement</asset_name>
                    <Origin>
                        <X>10</X>
                        <Y>50</Y>
                    </Origin>
                </Item>
                <Item xsi:type="TextureItem" Name="Texture_1799" Visible="true">
                    <Position>
                        <X>87</X>
                        <Y>-424</Y>
                    </Position>
                    <CustomProperties />
                    <Rotation>-1.57212389</Rotation>
                    <Scale>
                        <X>3.21105814</X>
                        <Y>3.21105814</Y>
                    </Scale>
                    <TintColor>
                        <R>255</R>
                        <G>255</G>
                        <B>255</B>
                        <A>255</A>
                        <PackedValue>4294967295</PackedValue>
                    </TintColor>
                    <FlipHorizontally>false</FlipHorizontally>
                    <FlipVertically>false</FlipVertically>
                    <texture_filename>Physical\cement.png</texture_filename>
                    <asset_name>Physical\cement</asset_name>
                    <Origin>
                        <X>10</X>
                        <Y>50</Y>
                    </Origin>
                </Item>
                <Item xsi:type="TextureItem" Name="Texture_1800" Visible="true">
                    <Position>
                        <X>283</X>
                        <Y>-554</Y>
                    </Position>
                    <CustomProperties />
                    <Rotation>0</Rotation>
                    <Scale>
                        <X>3.21105814</X>
                        <Y>3.21105814</Y>
                    </Scale>
                    <TintColor>
                        <R>255</R>
                        <G>255</G>
                        <B>255</B>
                        <A>255</A>
                        <PackedValue>4294967295</PackedValue>
                    </TintColor>
                    <FlipHorizontally>false</FlipHorizontally>
                    <FlipVertically>false</FlipVertically>
                    <texture_filename>Physical\cement.png</texture_filename>
                    <asset_name>Physical\cement</asset_name>
                    <Origin>
                        <X>10</X>
                        <Y>50</Y>
                    </Origin>
                </Item>
                <Item xsi:type="TextureItem" Name="Texture_1801" Visible="true">
                    <Position>
                        <X>403</X>
                        <Y>-750</Y>
                    </Position>
                    <CustomProperties />
                    <Rotation>-4.70699358</Rotation>
                    <Scale>
                        <X>3.21105814</X>
                        <Y>3.21105814</Y>
                    </Scale>
                    <TintColor>
                        <R>255</R>
                        <G>255</G>
                        <B>255</B>
                        <A>255</A>
                        <PackedValue>4294967295</PackedValue>
                    </TintColor>
                    <FlipHorizontally>false</FlipHorizontally>
                    <FlipVertically>false</FlipVertically>
                    <texture_filename>Physical\cement.png</texture_filename>
                    <asset_name>Physical\cement</asset_name>
                    <Origin>
                        <X>10</X>
                        <Y>50</Y>
                    </Origin>
                </Item>
                <Item xsi:type="TextureItem" Name="Texture_1802" Visible="true">
                    <Position>
                        <X>667</X>
                        <Y>-684</Y>
                    </Position>
                    <CustomProperties />
                    <Rotation>-4.70699358</Rotation>
                    <Scale>
                        <X>3.21105814</X>
                        <Y>3.21105814</Y>
                    </Scale>
                    <TintColor>
                        <R>255</R>
                        <G>255</G>
                        <B>255</B>
                        <A>255</A>
                        <PackedValue>4294967295</PackedValue>
                    </TintColor>
                    <FlipHorizontally>false</FlipHorizontally>
                    <FlipVertically>false</FlipVertically>
                    <texture_filename>Physical\cement.png</texture_filename>
                    <asset_name>Physical\cement</asset_name>
                    <Origin>
                        <X>10</X>
                        <Y>50</Y>
                    </Origin>
                </Item>
                <Item xsi:type="TextureItem" Name="Texture_1803" Visible="true">
                    <Position>
                        <X>681</X>
                        <Y>-524</Y>
                    </Position>
                    <CustomProperties />
                    <Rotation>-6.29819536</Rotation>
                    <Scale>
                        <X>3.21105814</X>
                        <Y>2.5</Y>
                    </Scale>
                    <TintColor>
                        <R>255</R>
                        <G>255</G>
                        <B>255</B>
                        <A>255</A>
                        <PackedValue>4294967295</PackedValue>
                    </TintColor>
                    <FlipHorizontally>false</FlipHorizontally>
                    <FlipVertically>false</FlipVertically>
                    <texture_filename>Physical\cement.png</texture_filename>
                    <asset_name>Physical\cement</asset_name>
                    <Origin>
                        <X>10</X>
                        <Y>50</Y>
                    </Origin>
                </Item>
                <Item xsi:type="TextureItem" Name="Texture_1808" Visible="true">
                    <Position>
                        <X>790</X>
                        <Y>-165</Y>
                    </Position>
                    <CustomProperties />
                    <Rotation>0</Rotation>
                    <Scale>
                        <X>3.21105814</X>
                        <Y>3.21105814</Y>
                    </Scale>
                    <TintColor>
                        <R>255</R>
                        <G>255</G>
                        <B>255</B>
                        <A>255</A>
                        <PackedValue>4294967295</PackedValue>
                    </TintColor>
                    <FlipHorizontally>false</FlipHorizontally>
                    <FlipVertically>false</FlipVertically>
                    <texture_filename>Physical\cement.png</texture_filename>
                    <asset_name>Physical\cement</asset_name>
                    <Origin>
                        <X>10</X>
                        <Y>50</Y>
                    </Origin>
                </Item>
                <Item xsi:type="TextureItem" Name="Texture_1810" Visible="true">
                    <Position>
                        <X>887</X>
                        <Y>-361</Y>
                    </Position>
                    <CustomProperties />
                    <Rotation>-7.85878372</Rotation>
                    <Scale>
                        <X>3.21105814</X>
                        <Y>2.5</Y>
                    </Scale>
                    <TintColor>
                        <R>255</R>
                        <G>255</G>
                        <B>255</B>
                        <A>255</A>
                        <PackedValue>4294967295</PackedValue>
                    </TintColor>
                    <FlipHorizontally>false</FlipHorizontally>
                    <FlipVertically>false</FlipVertically>
                    <texture_filename>Physical\cement.png</texture_filename>
                    <asset_name>Physical\cement</asset_name>
                    <Origin>
                        <X>10</X>
                        <Y>50</Y>
                    </Origin>
                </Item>
                <Item xsi:type="TextureItem" Name="Texture_1811" Visible="true">
                    <Position>
                        <X>980</X>
                        <Y>-165</Y>
                    </Position>
                    <CustomProperties />
                    <Rotation>0</Rotation>
                    <Scale>
                        <X>3.21105814</X>
                        <Y>3.21105814</Y>
                    </Scale>
                    <TintColor>
                        <R>255</R>
                        <G>255</G>
                        <B>255</B>
                        <A>255</A>
                        <PackedValue>4294967295</PackedValue>
                    </TintColor>
                    <FlipHorizontally>false</FlipHorizontally>
                    <FlipVertically>false</FlipVertically>
                    <texture_filename>Physical\cement.png</texture_filename>
                    <asset_name>Physical\cement</asset_name>
                    <Origin>
                        <X>10</X>
                        <Y>50</Y>
                    </Origin>
                </Item>
                <Item xsi:type="TextureItem" Name="Texture_1816" Visible="true">
                    <Position>
                        <X>930</X>
                        <Y>-495</Y>
                    </Position>
                    <CustomProperties />
                    <Rotation>0</Rotation>
                    <Scale>
                        <X>3.21105814</X>
                        <Y>2</Y>
                    </Scale>
                    <TintColor>
                        <R>255</R>
                        <G>255</G>
                        <B>255</B>
                        <A>255</A>
                        <PackedValue>4294967295</PackedValue>
                    </TintColor>
                    <FlipHorizontally>false</FlipHorizontally>
                    <FlipVertically>false</FlipVertically>
                    <texture_filename>Physical\wood.png</texture_filename>
                    <asset_name>Physical\wood</asset_name>
                    <Origin>
                        <X>10</X>
                        <Y>50</Y>
                    </Origin>
                </Item>
                <Item xsi:type="TextureItem" Name="Texture_1817" Visible="true">
                    <Position>
                        <X>934</X>
                        <Y>-628</Y>
                    </Position>
                    <CustomProperties />
                    <Rotation>-1.56994593</Rotation>
                    <Scale>
                        <X>3.21105814</X>
                        <Y>2</Y>
                    </Scale>
                    <TintColor>
                        <R>255</R>
                        <G>255</G>
                        <B>255</B>
                        <A>255</A>
                        <PackedValue>4294967295</PackedValue>
                    </TintColor>
                    <FlipHorizontally>false</FlipHorizontally>
                    <FlipVertically>false</FlipVertically>
                    <texture_filename>Physical\wood.png</texture_filename>
                    <asset_name>Physical\wood</asset_name>
                    <Origin>
                        <X>10</X>
                        <Y>50</Y>
                    </Origin>
                </Item>
                <Item xsi:type="TextureItem" Name="Texture_1834" Visible="true">
                    <Position>
                        <X>785</X>
                        <Y>-845</Y>
                    </Position>
                    <CustomProperties />
                    <Rotation>-6.29819536</Rotation>
                    <Scale>
                        <X>3.21105814</X>
                        <Y>2.5</Y>
                    </Scale>
                    <TintColor>
                        <R>255</R>
                        <G>255</G>
                        <B>255</B>
                        <A>255</A>
                        <PackedValue>4294967295</PackedValue>
                    </TintColor>
                    <FlipHorizontally>false</FlipHorizontally>
                    <FlipVertically>false</FlipVertically>
                    <texture_filename>Physical\cement.png</texture_filename>
                    <asset_name>Physical\cement</asset_name>
                    <Origin>
                        <X>10</X>
                        <Y>50</Y>
                    </Origin>
                </Item>
                <Item xsi:type="TextureItem" Name="Texture_1842" Visible="true">
                    <Position>
                        <X>562</X>
                        <Y>-1203</Y>
                    </Position>
                    <CustomProperties />
                    <Rotation>-7.85043144</Rotation>
                    <Scale>
                        <X>2.16949821</X>
                        <Y>4</Y>
                    </Scale>
                    <TintColor>
                        <R>255</R>
                        <G>255</G>
                        <B>255</B>
                        <A>255</A>
                        <PackedValue>4294967295</PackedValue>
                    </TintColor>
                    <FlipHorizontally>false</FlipHorizontally>
                    <FlipVertically>false</FlipVertically>
                    <texture_filename>Physical\cement.png</texture_filename>
                    <asset_name>Physical\cement</asset_name>
                    <Origin>
                        <X>10</X>
                        <Y>50</Y>
                    </Origin>
                </Item>
            </Items>
            <ScrollSpeed>
                <X>1</X>
                <Y>1</Y>
            </ScrollSpeed>
            <CustomProperties>
                <Property Name="Mass" Type="string" Description="5">
                    <string>100</string>
                </Property>
                <Property Name="Type" Type="string" Description="Circle">
                    <string>Circle</string>
                </Property>
                <Property Name="LayerDepth" Type="string" Description="0">
                    <string>0</string>
                </Property>
                <Property Name="Friction" Type="string" Description="">
                    <string>10</string>
                </Property>
            </CustomProperties>
        </Layer>
        <Layer Name="Sprite#1" Visible="true">
            <Items>
                <Item xsi:type="TextureItem" Name="Texture_1849" Visible="true">
                    <Position>
                        <X>266</X>
                        <Y>-870</Y>
                    </Position>
                    <CustomProperties />
                    <Rotation>0</Rotation>
                    <Scale>
                        <X>1</X>
                        <Y>1</Y>
                    </Scale>
                    <TintColor>
                        <R>255</R>
                        <G>255</G>
                        <B>255</B>
                        <A>255</A>
                        <PackedValue>4294967295</PackedValue>
                    </TintColor>
                    <FlipHorizontally>false</FlipHorizontally>
                    <FlipVertically>false</FlipVertically>
                    <texture_filename>donutcase.png</texture_filename>
                    <asset_name>donutcase</asset_name>
                    <Origin>
                        <X>66</X>
                        <Y>81</Y>
                    </Origin>
                </Item>
                <Item xsi:type="TextureItem" Name="Texture_1850" Visible="true">
                    <Position>
                        <X>472</X>
                        <Y>-1314</Y>
                    </Position>
                    <CustomProperties />
                    <Rotation>0</Rotation>
                    <Scale>
                        <X>1</X>
                        <Y>1</Y>
                    </Scale>
                    <TintColor>
                        <R>255</R>
                        <G>255</G>
                        <B>255</B>
                        <A>255</A>
                        <PackedValue>4294967295</PackedValue>
                    </TintColor>
                    <FlipHorizontally>false</FlipHorizontally>
                    <FlipVertically>false</FlipVertically>
                    <texture_filename>donutcase.png</texture_filename>
                    <asset_name>donutcase</asset_name>
                    <Origin>
                        <X>66</X>
                        <Y>81</Y>
                    </Origin>
                </Item>
                <Item xsi:type="TextureItem" Name="Texture_1851" Visible="true">
                    <Position>
                        <X>622</X>
                        <Y>-1310</Y>
                    </Position>
                    <CustomProperties />
                    <Rotation>0</Rotation>
                    <Scale>
                        <X>1</X>
                        <Y>1</Y>
                    </Scale>
                    <TintColor>
                        <R>255</R>
                        <G>255</G>
                        <B>255</B>
                        <A>255</A>
                        <PackedValue>4294967295</PackedValue>
                    </TintColor>
                    <FlipHorizontally>false</FlipHorizontally>
                    <FlipVertically>false</FlipVertically>
                    <texture_filename>donutcase.png</texture_filename>
                    <asset_name>donutcase</asset_name>
                    <Origin>
                        <X>66</X>
                        <Y>81</Y>
                    </Origin>
                </Item>
                <Item xsi:type="TextureItem" Name="Texture_1852" Visible="true">
                    <Position>
                        <X>535</X>
                        <Y>-1481</Y>
                    </Position>
                    <CustomProperties />
                    <Rotation>0</Rotation>
                    <Scale>
                        <X>1</X>
                        <Y>1</Y>
                    </Scale>
                    <TintColor>
                        <R>255</R>
                        <G>255</G>
                        <B>255</B>
                        <A>255</A>
                        <PackedValue>4294967295</PackedValue>
                    </TintColor>
                    <FlipHorizontally>false</FlipHorizontally>
                    <FlipVertically>false</FlipVertically>
                    <texture_filename>donutcase.png</texture_filename>
                    <asset_name>donutcase</asset_name>
                    <Origin>
                        <X>66</X>
                        <Y>81</Y>
                    </Origin>
                </Item>
                <Item xsi:type="TextureItem" Name="Texture_1853" Visible="true">
                    <Position>
                        <X>563</X>
                        <Y>-1596</Y>
                    </Position>
                    <CustomProperties />
                    <Rotation>-3.151482</Rotation>
                    <Scale>
                        <X>1</X>
                        <Y>1</Y>
                    </Scale>
                    <TintColor>
                        <R>255</R>
                        <G>255</G>
                        <B>255</B>
                        <A>255</A>
                        <PackedValue>4294967295</PackedValue>
                    </TintColor>
                    <FlipHorizontally>false</FlipHorizontally>
                    <FlipVertically>false</FlipVertically>
                    <texture_filename>fan.png</texture_filename>
                    <asset_name>fan</asset_name>
                    <Origin>
                        <X>128</X>
                        <Y>128</Y>
                    </Origin>
                </Item>
            </Items>
            <ScrollSpeed>
                <X>1</X>
                <Y>1</Y>
            </ScrollSpeed>
            <CustomProperties>
                <Property Name="LayerDepth" Type="string" Description="">
                    <string>0.1</string>
                </Property>
            </CustomProperties>
        </Layer>
        <Layer Name="TNT" Visible="true">
            <Items />
            <ScrollSpeed>
                <X>1</X>
                <Y>1</Y>
            </ScrollSpeed>
            <CustomProperties />
        </Layer>
        <Layer Name="RigidBodies" Visible="true">
            <Items />
            <ScrollSpeed>
                <X>1</X>
                <Y>1</Y>
            </ScrollSpeed>
            <CustomProperties>
                <Property Name="Mass" Type="string" Description="">
                    <string>60</string>
                </Property>
                <Property Name="Type" Type="string" Description="">
                    <string>Circle</string>
                </Property>
            </CustomProperties>
        </Layer>
        <Layer Name="Sprite#2" Visible="true">
            <Items />
            <ScrollSpeed>
                <X>1</X>
                <Y>1</Y>
            </ScrollSpeed>
            <CustomProperties>
                <Property Name="LayerDepth" Type="string" Description="">
                    <string>0</string>
                </Property>
            </CustomProperties>
        </Layer>
        <Layer Name="BreakableShapeRigidBodies" Visible="true">
            <Items />
            <ScrollSpeed>
                <X>1</X>
                <Y>1</Y>
            </ScrollSpeed>
            <CustomProperties>
                <Property Name="Mass" Type="string" Description="5">
                    <string>100</string>
                </Property>
                <Property Name="Type" Type="string" Description="Circle">
                    <string>Circle</string>
                </Property>
                <Property Name="LayerDepth" Type="string" Description="0">
                    <string>0</string>
                </Property>
                <Property Name="Friction" Type="string" Description="">
                    <string>10</string>
                </Property>
            </CustomProperties>
        </Layer>
    </Layers>
    <CustomProperties>
        <Property Name="CamStartPos" Type="Vector2" Description="">
            <Vector2>
                <X>49</X>
                <Y>561</Y>
            </Vector2>
        </Property>
        <Property Name="SpotStartPos" Type="Vector2" Description="">
            <Vector2>
                <X>-383</X>
                <Y>485</Y>
            </Vector2>
        </Property>
        <Property Name="CamStartScale" Type="string" Description="0.1">
            <string>0.35</string>
        </Property>
        <Property Name="MaxGameCamPos" Type="Vector2" Description="">
            <Vector2>
                <X>969</X>
                <Y>460</Y>
            </Vector2>
        </Property>
        <Property Name="ScaleAtMax" Type="string" Description="0.2">
            <string>0.35</string>
        </Property>
        <Property Name="MinCamPos" Type="string" Description="">
            <string>-1500</string>
        </Property>
        <Property Name="MaxCamPos" Type="string" Description="">
            <string>4000</string>
        </Property>
        <Property Name="LeftInvisibleWall" Type="string" Description="">
            <string>-2500</string>
        </Property>
        <Property Name="RightInvisibleWall" Type="string" Description="">
            <string>3000</string>
        </Property>
        <Property Name="MaxCamTarget" Type="string" Description="">
            <string>400</string>
        </Property>
        <Property Name="Chicks" Type="string" Description="">
            <string>3+0+0</string>
        </Property>
        <Property Name="RigidBody" Type="string" Description="">
            <string />
        </Property>
        <Property Name="Sprite#2" Type="string" Description="">
            <string />
        </Property>
        <Property Name="WorldDir" Type="string" Description="">
            <string>Paris</string>
        </Property>
    </CustomProperties>
    <EditorRelated>
        <NextItemNumber>1854</NextItemNumber>
        <ContentRootFolder>C:\mobile\Hen\Hen\HenContent\Textures</ContentRootFolder>
        <CameraPosition>
            <X>324.5416</X>
            <Y>-967.1633</Y>
        </CameraPosition>
        <Version>1.3.0.0</Version>
    </EditorRelated>
</Level>